autoscroll/__init__.py
autoscroll/__main__.py
autoscroll/main.py
autoscroll/autoscroll/__init__.py
autoscroll/autoscroll/arguments.py
autoscroll/autoscroll/autoscroll.py
autoscroll/autoscroll/constants.py
autoscroll/autoscroll/functions.py
autoscroll/autoscroll/qt.py
autoscroll/autoscroll/support.py
autoscroll/resources/img/empty.svg
autoscroll/resources/img/icon.svg
autoscroll/resources/img/white.svg
autoscroll/resources/txt/prolog.txt
autoscroll-1.0.0.dist-info/LICENSE
autoscroll-1.0.0.dist-info/METADATA
autoscroll-1.0.0.dist-info/WHEEL
autoscroll-1.0.0.dist-info/entry_points.txt
autoscroll-1.0.0.dist-info/top_level.txt
autoscroll-1.0.0.dist-info/RECORD
