Metadata-Version: 2.1
Name: autoscroll
Version: 1.0.0
Summary: Enables universal autoscroll
Home-page: https://github.com/kongrentian/autoscroll
Author: kongrentian
Author-email: causelesscause@gmail.com
License: GNU General Public License v3.0
Platform: UNKNOWN
Classifier: License :: OSI Approved :: GNU General Public License v3 (GPLv3)
Classifier: Programming Language :: Python :: 3
Classifier: Programming Language :: Python :: 3.6
Classifier: Operating System :: OS Independent
Requires-Python: >=3.6
License-File: LICENSE
Requires-Dist: pynput
Provides-Extra: icon
Requires-Dist: pyside6 ; extra == 'icon'
